switch/__init__.py
switch/switch.py
exception_logic_BridgeTechIL-0.1.4.dist-info/LICENSE.md
exception_logic_BridgeTechIL-0.1.4.dist-info/METADATA
exception_logic_BridgeTechIL-0.1.4.dist-info/WHEEL
exception_logic_BridgeTechIL-0.1.4.dist-info/top_level.txt
exception_logic_BridgeTechIL-0.1.4.dist-info/RECORD
