Metadata-Version: 2.1
Name: exception-logic-BridgeTechIL
Version: 0.1.4
Summary: Switch logic for the smart elevators
Home-page: https://github.com/pypa/sampleproject
Author: BridgeTechIL
Author-email: antonchagan@gmail.com
License: UNKNOWN
Project-URL: Bug Tracker, https://github.com/antonchagan/EL_BridgeTech/issues
Platform: UNKNOWN
Classifier: Programming Language :: Python :: 3
Classifier: License :: OSI Approved :: MIT License
Classifier: Operating System :: OS Independent
Requires-Python: >=3.7
License-File: LICENSE.md
